finance_tracker/__init__.py
finance_tracker/__main__.py
finance_tracker/aggregators/__init__.py
finance_tracker/aggregators/aggregator_by_month.py
finance_tracker/aggregators/categories_quantity_aggregator.py
finance_tracker/categories/__init__.py
finance_tracker/categories/categories.py
finance_tracker/categories/categorizer.py
finance_tracker/categories/category_searcher.py
finance_tracker/entries/__init__.py
finance_tracker/entries/categorized_entry.py
finance_tracker/entries/entry.py
finance_tracker/entries/revolut_entry.py
finance_tracker/money/__init__.py
finance_tracker/money/currency_codes.py
finance_tracker/money/money.py
finance_tracker/printer.py
finance_tracker/readers/__init__.py
finance_tracker/readers/base_reader.py
finance_tracker/readers/entry_reader.py
finance_tracker/readers/revolut_reader.py
finance_tracker-1.3.0.dist-info/LICENSE
finance_tracker-1.3.0.dist-info/WHEEL
finance_tracker-1.3.0.dist-info/METADATA
finance_tracker-1.3.0.dist-info/RECORD
