Metadata-Version: 2.1
Name: finance-tracker
Version: 1.3.0
Summary: Python tool to track finances over a year
Home-page: https://github.com/w0rmr1d3r/finance-tracker
License: MIT
Keywords: finance,tracker,poetry
Author: w0rmr1d3r
Requires-Python: >=3.9,<4.0
Classifier: Development Status :: 5 - Production/Stable
Classifier: Environment :: Console
Classifier: Intended Audience :: Developers
Classifier: Intended Audience :: Education
Classifier: Intended Audience :: Financial and Insurance Industry
Classifier: License :: OSI Approved :: MIT License
Classifier: Programming Language :: Python
Classifier: Programming Language :: Python :: 3
Classifier: Programming Language :: Python :: 3.9
Classifier: Programming Language :: Python :: 3.10
Classifier: Programming Language :: Python :: 3.11
Classifier: Programming Language :: Python :: 3
Classifier: Programming Language :: Python :: 3 :: Only
Classifier: Programming Language :: Python :: 3.10
Classifier: Programming Language :: Python :: 3.11
Classifier: Programming Language :: Python :: 3.9
Classifier: Topic :: Office/Business
Classifier: Topic :: Office/Business :: Financial
Classifier: Topic :: Office/Business :: Financial :: Accounting
Classifier: Typing :: Typed
Requires-Dist: Deprecated (>=1.2.13,<2.0.0)
Requires-Dist: inquirer (>=2.10.0,<3.0.0)
Requires-Dist: pandas (>=1.5.0,<2.0.0)
Project-URL: Documentation, https://github.com/w0rmr1d3r/finance-tracker
Project-URL: Repository, https://github.com/w0rmr1d3r/finance-tracker
